paracord/__init__.py
paracord/cli.py
paracord/commands/__init__.py
paracord/commands/bug.py
paracord/commands/check.py
paracord/commands/component.py
paracord/commands/init.py
paracord/commands/run.py
paracord/commands/sync.py
paracord/commands/update.py
paracord/core/__init__.py
paracord/core/component_installer.py
paracord/core/components.py
paracord/core/context.py
paracord/core/copier.py
paracord/core/github.py
paracord/core/project_registry.py
paracord/core/rav.py
paracord/core/registry.py
paracord/utils/__init__.py
paracord/utils/config.py
paracord/utils/console.py
paracord/utils/git.py
paracord/utils/version_check.py
paracord-0.0.8.dist-info/METADATA
paracord-0.0.8.dist-info/WHEEL
paracord-0.0.8.dist-info/entry_points.txt
paracord-0.0.8.dist-info/RECORD
