Metadata-Version: 2.4
Name: paracord
Version: 0.0.8
Summary: A modern CLI tool for Paracord projects - wraps copier, uv, and rav into a unified developer experience
Project-URL: Homepage, https://github.com/getparacord/paracord
Project-URL: Repository, https://github.com/getparacord/paracord
Project-URL: Issues, https://github.com/getparacord/paracord/issues
Author-email: Justin Mitchel <getparacord@gmail.com>
Maintainer-email: jmitchel3 <getparacord@gmail.com>
License-Expression: MIT
Keywords: cli,copier,paracord,project-template,rav,uv
Classifier: Development Status :: 3 - Alpha
Classifier: Environment :: Console
Classifier: Intended Audience :: Developers
Classifier: License :: OSI Approved :: MIT License
Classifier: Operating System :: OS Independent
Classifier: Programming Language :: Python :: 3
Classifier: Programming Language :: Python :: 3.12
Classifier: Programming Language :: Python :: 3.13
Classifier: Topic :: Software Development :: Build Tools
Requires-Python: >=3.12
Requires-Dist: copier>=9.0.0
Requires-Dist: httpx>=0.25.0
Requires-Dist: keyring>=24.0.0
Requires-Dist: pyyaml>=6.0
Requires-Dist: rich>=13.0.0
Requires-Dist: tomli-w>=1.0.0
Requires-Dist: typer>=0.9.0
Provides-Extra: console
Requires-Dist: fastapi>=0.104.0; extra == 'console'
Requires-Dist: jinja2>=3.1.0; extra == 'console'
Requires-Dist: uvicorn>=0.24.0; extra == 'console'
